deepdiff/__init__.py
deepdiff/contenthash.py
deepdiff/diff.py
deepdiff/helper.py
deepdiff/search.py
deepdiff_balance-0.1.0.dist-info/LICENSE
deepdiff_balance-0.1.0.dist-info/WHEEL
deepdiff_balance-0.1.0.dist-info/METADATA
deepdiff_balance-0.1.0.dist-info/RECORD
